CHANGES.txt
LICENSE.txt
MANIFEST.in
README.rst
example.ini
setup.py
sqs_consumer/__init__.py
sqs_consumer/dispatchers.py
sqs_consumer/interfaces.py
sqs_consumer/workers.py
sqs_consumer.egg-info/PKG-INFO
sqs_consumer.egg-info/SOURCES.txt
sqs_consumer.egg-info/dependency_links.txt
sqs_consumer.egg-info/entry_points.txt
sqs_consumer.egg-info/not-zip-safe
sqs_consumer.egg-info/requires.txt
sqs_consumer.egg-info/top_level.txt
sqs_consumer/tests/__init__.py
sqs_consumer/tests/dispatcher_fake1.py
sqs_consumer/tests/example.py
sqs_consumer/tests/test_dispatchers.py
sqs_consumer/tests/test_workers.py