Metadata-Version: 1.1
Name: sqs-consumer
Version: 0.1
Summary: AWS SQS Consumer helper
Home-page: https://github.com/gjo/sqs_consumer
Author: OCHIAI, Gouji
Author-email: gjo.ext@gmail.com
License: BSD
Platform: UNKNOWN
Classifier: License :: OSI Approved :: BSD License
Classifier: Programming Language :: Python
Classifier: Programming Language :: Python :: 3.4
